{
  "AEK": 1678.03,
  "AVS": 1374.25,
  "AZ Alkmaar": 1695.84,
  "Aberdeen": 1469.61,
  "Ad. Demirspor": 1259.55,
  "Ajaccio": 1416.11,
  "Ajaccio GFCO": 1373.18,
  "Ajax": 1776.94,
  "Akhisar Belediyespor": 1340.3,
  "Alanyaspor": 1569.54,
  "Alaves": 1609.13,
  "Albacete": 1481.43,
  "Alcorcon": 1413.97,
  "Alessandria": 1329.75,
  "Almere City": 1375.25,
  "Almeria": 1522.89,
  "Altay": 1392.84,
  "Amiens": 1382.22,
  "Amorebieta": 1452.99,
  "Anderlecht": 1662.43,
  "Andorra": 1388.51,
  "Angers": 1558.48,
  "Ankaragucu": 1476.19,
  "Annecy": 1449.11,
  "Antalyaspor": 1482.08,
  "Antwerp": 1617.81,
  "Apollon": 1312.37,
  "Aris": 1670.31,
  "Arouca": 1535.76,
  "Arsenal": 1904.56,
  "Ascoli": 1424.53,
  "Asteras Tripolis": 1501.42,
  "Aston Villa": 1810.05,
  "Atalanta": 1850.6,
  "Ath Bilbao": 1799.55,
  "Ath Madrid": 1803.21,
  "Athens Kallithea": 1440.19,
  "Atromitos": 1556.74,
  "Augsburg": 1578.57,
  "Auxerre": 1653.27,
  "Aves": 1246.94,
  "Barcelona": 1949.13,
  "Bari": 1420.63,
  "Barnsley": 1217.73,
  "Bastia": 1469.93,
  "Bayern Munich": 1944.96,
  "Beerschot VA": 1360.44,
  "Belenenses": 1399.67,
  "Benevento": 1330.0,
  "Benfica": 1905.06,
  "Besiktas": 1663.82,
  "Betis": 1715.65,
  "Beziers": 1445.99,
  "Bielefeld": 1371.28,
  "Birmingham": 1338.2,
  "Blackburn": 1416.62,
  "Blackpool": 1293.69,
  "Boavista": 1355.42,
  "Bochum": 1485.13,
  "Bodrumspor": 1489.02,
  "Bologna": 1733.7,
  "Bolton": 1228.49,
  "Bordeaux": 1438.18,
  "Bournemouth": 1723.08,
  "Braunschweig": 1375.75,
  "Brentford": 1738.79,
  "Brescia": 1427.12,
  "Brest": 1686.59,
  "Brighton": 1781.22,
  "Bristol City": 1469.66,
  "Burgos": 1446.99,
  "Burnley": 1727.73,
  "Bursaspor": 1447.77,
  "Buyuksehyr": 1587.27,
  "Cadiz": 1469.41,
  "Caen": 1241.26,
  "Cagliari": 1570.01,
  "Cambuur": 1305.1,
  "Cardiff": 1292.11,
  "Carpi": 1341.59,
  "Carrarese": 1418.47,
  "Cartagena": 1226.76,
  "Casa Pia": 1528.94,
  "Castellon": 1436.41,
  "Catanzaro": 1492.94,
  "Celta": 1673.7,
  "Celtic": 1856.08,
  "Cercle Brugge": 1455.47,
  "Cesena": 1482.45,
  "Chambly": 1409.49,
  "Charleroi": 1630.0,
  "Charlton": 1356.0,
  "Chateauroux": 1261.84,
  "Chaves": 1357.28,
  "Chelsea": 1828.31,
  "Chievo": 1496.32,
  "Cittadella": 1322.6,
  "Clermont": 1347.85,
  "Club Brugge": 1883.36,
  "Como": 1710.44,
  "Concarneau": 1322.78,
  "Cordoba": 1444.51,
  "Cosenza": 1293.35,
  "Coventry": 1476.44,
  "Cremonese": 1566.65,
  "Crotone": 1306.06,
  "Crystal Palace": 1777.69,
  "Darmstadt": 1412.88,
  "Den Haag": 1289.78,
  "Dender": 1492.05,
  "Denizlispor": 1278.12,
  "Derby": 1397.12,
  "Dijon": 1428.37,
  "Dortmund": 1809.25,
  "Dresden": 1301.79,
  "Duisburg": 1373.13,
  "Dundee": 1427.96,
  "Dundee United": 1468.66,
  "Dunkerque": 1462.29,
  "Eibar": 1508.78,
  "Ein Frankfurt": 1763.46,
  "Elche": 1607.78,
  "Eldense": 1360.93,
  "Elversberg": 1584.55,
  "Empoli": 1500.67,
  "Erzgebirge Aue": 1274.17,
  "Erzurum BB": 1426.02,
  "Espanol": 1600.37,
  "Estoril": 1582.77,
  "Estrela": 1388.96,
  "Eupen": 1312.12,
  "Everton": 1748.85,
  "Excelsior": 1400.3,
  "Extremadura UD": 1414.75,
  "Eyupspor": 1507.64,
  "FC Emmen": 1399.75,
  "FC Koln": 1557.85,
  "Famalicao": 1591.99,
  "Farense": 1423.3,
  "Feirense": 1286.0,
  "Fenerbahce": 1875.74,
  "FeralpiSalo": 1352.09,
  "Ferrol": 1247.27,
  "Feyenoord": 1815.35,
  "Fiorentina": 1779.5,
  "Foggia": 1461.75,
  "For Sittard": 1471.85,
  "Fortuna Dusseldorf": 1500.41,
  "Freiburg": 1680.71,
  "Frosinone": 1455.34,
  "Fuenlabrada": 1305.64,
  "Fulham": 1687.04,
  "Galatasaray": 2011.03,
  "Gaziantep": 1507.28,
  "Genclerbirligi": 1391.95,
  "Genk": 1749.26,
  "Genoa": 1648.61,
  "Gent": 1496.77,
  "Getafe": 1538.79,
  "Giannina": 1337.14,
  "Gil Vicente": 1468.43,
  "Gimnastic": 1393.56,
  "Giresunspor": 1493.3,
  "Girona": 1513.22,
  "Go Ahead Eagles": 1567.73,
  "Goztep": 1525.18,
  "Graafschap": 1375.79,
  "Granada": 1496.3,
  "Grenoble": 1431.68,
  "Greuther Furth": 1386.73,
  "Groningen": 1482.66,
  "Guimaraes": 1649.83,
  "Guingamp": 1495.77,
  "Hamburg": 1576.15,
  "Hamilton": 1337.88,
  "Hannover": 1487.93,
  "Hansa Rostock": 1277.06,
  "Hatayspor": 1406.77,
  "Hearts": 1588.03,
  "Heerenveen": 1527.75,
  "Heidenheim": 1524.92,
  "Heracles": 1486.24,
  "Hertha": 1447.58,
  "Hibernian": 1663.07,
  "Hoffenheim": 1551.39,
  "Holstein Kiel": 1509.27,
  "Huddersfield": 1287.41,
  "Huesca": 1446.25,
  "Hull": 1373.71,
  "Ibiza": 1341.53,
  "Ingolstadt": 1277.26,
  "Inter": 1941.65,
  "Ionikos": 1405.5,
  "Ipswich": 1424.55,
  "Istanbulspor": 1293.46,
  "Juve Stabia": 1452.54,
  "Juventus": 1820.85,
  "Kaiserslautern": 1459.6,
  "Karagumruk": 1516.53,
  "Karlsruhe": 1511.52,
  "Kasimpasa": 1561.94,
  "Kayserispor": 1574.39,
  "Kifisia": 1347.82,
  "Kilmarnock": 1455.77,
  "Konyaspor": 1528.15,
  "Kortrijk": 1476.47,
  "La Coruna": 1426.67,
  "Lamia": 1273.97,
  "Larisa": 1378.03,
  "Las Palmas": 1448.68,
  "Laval": 1453.24,
  "Lazio": 1765.49,
  "Le Havre": 1567.9,
  "Le Mans": 1404.53,
  "Lecce": 1554.24,
  "Lecco": 1231.53,
  "Leeds": 1706.07,
  "Leganes": 1565.83,
  "Leicester": 1446.45,
  "Lens": 1708.07,
  "Levadeiakos": 1543.41,
  "Levante": 1657.74,
  "Leverkusen": 1877.15,
  "Lille": 1774.98,
  "Liverpool": 1911.87,
  "Livingston": 1296.17,
  "Livorno": 1216.0,
  "Logrones": 1365.63,
  "Lokeren": 1330.26,
  "Lorient": 1631.6,
  "Lugo": 1290.69,
  "Luton": 1391.4,
  "Lyon": 1772.28,
  "M'gladbach": 1566.81,
  "Magdeburg": 1469.72,
  "Mainz": 1701.1,
  "Malaga": 1415.16,
  "Mallorca": 1555.63,
  "Man City": 1916.39,
  "Man United": 1606.26,
  "Mantova": 1427.35,
  "Maritimo": 1398.03,
  "Marseille": 1777.21,
  "Martigues": 1374.51,
  "Mechelen": 1546.88,
  "Metz": 1611.35,
  "Middlesbrough": 1388.28,
  "Milan": 1791.55,
  "Millwall": 1462.76,
  "Mirandes": 1580.4,
  "Modena": 1405.54,
  "Monaco": 1785.65,
  "Montpellier": 1368.19,
  "Monza": 1383.53,
  "Moreirense": 1517.55,
  "Motherwell": 1458.4,
  "Mouscron": 1386.57,
  "NAC Breda": 1360.41,
  "Nacional": 1412.19,
  "Nancy": 1258.74,
  "Nantes": 1575.29,
  "Napoli": 1881.08,
  "Newcastle": 1784.5,
  "Nice": 1796.29,
  "Nijmegen": 1593.4,
  "Nimes": 1334.12,
  "Niort": 1253.46,
  "Norwich": 1370.46,
  "Nott'm Forest": 1724.71,
  "Numancia": 1410.9,
  "Nurnberg": 1445.53,
  "OFI Crete": 1476.12,
  "Olympiakos": 1935.94,
  "Oostende": 1352.12,
  "Orleans": 1319.59,
  "Osasuna": 1679.33,
  "Osnabruck": 1304.21,
  "Oud-Heverlee Leuven": 1451.23,
  "Oviedo": 1603.39,
  "Oxford": 1393.15,
  "PAOK": 1769.66,
  "PSV Eindhoven": 1909.95,
  "Pacos Ferreira": 1397.75,
  "Paderborn": 1505.6,
  "Padova": 1432.5,
  "Palermo": 1485.51,
  "Panathinaikos": 1759.29,
  "Panetolikos": 1471.34,
  "Panionios": 1398.23,
  "Panserraikos": 1410.1,
  "Paris FC": 1613.69,
  "Paris SG": 1993.81,
  "Parma": 1605.5,
  "Pau FC": 1366.51,
  "Pendikspor": 1440.77,
  "Perugia": 1385.49,
  "Pescara": 1300.56,
  "Peterboro": 1327.5,
  "Pisa": 1584.49,
  "Plymouth": 1366.26,
  "Ponferradina": 1435.26,
  "Pordenone": 1200.47,
  "Portimonense": 1428.44,
  "Porto": 1759.18,
  "Portsmouth": 1412.7,
  "Preston": 1331.67,
  "Preußen Münster": 1455.0,
  "QPR": 1403.18,
  "Quevilly Rouen": 1404.11,
  "RB Leipzig": 1678.95,
  "RWD Molenbeek": 1334.51,
  "Rangers": 1737.03,
  "Rayo Majadahonda": 1407.91,
  "Reading": 1301.23,
  "Real Madrid": 1900.09,
  "Red Star": 1370.57,
  "Regensburg": 1292.78,
  "Reggiana": 1419.16,
  "Reggina": 1427.71,
  "Reims": 1528.59,
  "Rennes": 1652.2,
  "Reus Deportiu": 1183.65,
  "Rio Ave": 1506.88,
  "Rizespor": 1578.99,
  "Rodez": 1446.14,
  "Roma": 1884.15,
  "Ross County": 1349.85,
  "Rotherham": 1200.62,
  "Sabadell": 1477.34,
  "Salernitana": 1413.1,
  "Sampdoria": 1418.53,
  "Samsunspor": 1625.45,
  "Sandhausen": 1274.17,
  "Santa Clara": 1603.89,
  "Santander": 1506.47,
  "Sassuolo": 1599.24,
  "Schalke 04": 1352.72,
  "Seraing": 1274.46,
  "Setubal": 1390.08,
  "Sevilla": 1543.49,
  "Sheffield United": 1526.63,
  "Sheffield Weds": 1374.11,
  "Sivasspor": 1451.9,
  "Sochaux": 1362.3,
  "Sociedad": 1557.88,
  "Sociedad B": 1368.26,
  "Southampton": 1351.07,
  "Sp Braga": 1756.27,
  "Sp Gijon": 1443.73,
  "Sp Lisbon": 1960.04,
  "Spal": 1386.96,
  "Sparta Rotterdam": 1569.1,
  "Spezia": 1524.58,
  "St Etienne": 1540.88,
  "St Johnstone": 1331.54,
  "St Mirren": 1559.94,
  "St Pauli": 1530.69,
  "St Truiden": 1487.93,
  "St. Gilloise": 1927.41,
  "Standard": 1480.09,
  "Stoke": 1376.42,
  "Strasbourg": 1770.36,
  "Stuttgart": 1709.21,
  "Sudtirol": 1474.08,
  "Sunderland": 1390.24,
  "Swansea": 1444.63,
  "Tenerife": 1369.34,
  "Ternana": 1443.44,
  "Tondela": 1385.44,
  "Torino": 1617.33,
  "Tottenham": 1552.82,
  "Toulouse": 1651.32,
  "Trabzonspor": 1634.5,
  "Trapani": 1551.66,
  "Troyes": 1464.7,
  "Twente": 1637.68,
  "Udinese": 1546.83,
  "Ulm": 1360.47,
  "Umraniyespor": 1427.29,
  "Union Berlin": 1574.23,
  "Utrecht": 1699.26,
  "VVV Venlo": 1266.19,
  "Valencia": 1652.15,
  "Valenciennes": 1293.44,
  "Valladolid": 1306.85,
  "Vallecano": 1637.55,
  "Venezia": 1520.26,
  "Verona": 1565.33,
  "Vicenza": 1409.94,
  "Villarreal": 1815.54,
  "Villarreal B": 1395.74,
  "Virtus Entella": 1216.65,
  "Vitesse": 1402.78,
  "Vizela": 1389.66,
  "Volendam": 1291.01,
  "Volos NFC": 1443.57,
  "Waalwijk": 1433.08,
  "Waasland-Beveren": 1349.16,
  "Waregem": 1379.5,
  "Watford": 1317.02,
  "Wehen": 1271.64,
  "Werder Bremen": 1695.05,
  "West Brom": 1408.7,
  "West Ham": 1617.28,
  "Westerlo": 1563.69,
  "Wigan": 1322.52,
  "Willem II": 1307.23,
  "Wolfsburg": 1597.43,
  "Wolves": 1643.65,
  "Wurzburger Kickers": 1314.27,
  "Wycombe": 1430.39,
  "Xanthi": 1390.83,
  "Yeni Malatyaspor": 1235.21,
  "Zaragoza": 1389.28,
  "Zwolle": 1559.6
}